{"configPath":"/Users/Rohin1/code/github.com/website/wrangler.jsonc","userConfigPath":"/Users/Rohin1/code/github.com/website/wrangler.jsonc","topLevelName":"my-astro-app","definedEnvironments":[],"legacy_env":true,"compatibility_date":"2026-03-12","compatibility_flags":["global_fetch_strictly_public"],"jsx_factory":"React.createElement","jsx_fragment":"React.Fragment","rules":[{"type":"ESModule","globs":["**/*.js","**/*.mjs"]}],"name":"my-astro-app","main":"entry.mjs","triggers":{},"assets":{"directory":"../client","binding":"ASSETS"},"vars":{},"durable_objects":{"bindings":[]},"workflows":[],"migrations":[],"kv_namespaces":[{"binding":"SESSION"}],"cloudchamber":{},"send_email":[],"queues":{"producers":[],"consumers":[]},"r2_buckets":[],"d1_databases":[],"vectorize":[],"hyperdrive":[],"services":[],"analytics_engine_datasets":[],"dispatch_namespaces":[],"mtls_certificates":[],"images":{"binding":"IMAGES"},"pipelines":[],"secrets_store_secrets":[],"unsafe_hello_world":[],"worker_loaders":[],"ratelimits":[],"vpc_services":[],"logfwdr":{"bindings":[]},"observability":{"enabled":true},"python_modules":{"exclude":["**/*.pyc"]},"dev":{"ip":"localhost","local_protocol":"http","upstream_protocol":"http","enable_containers":true,"generate_types":false},"no_bundle":true}